harmonia/checker.py
harmonia/cli.py
harmonia/config.py
harmonia/dictionary.py
harmonia/formatters.py
harmonia/suggest.py
harmonia/utils.py
harmoniapy-1.2.0.dist-info/LICENSE
harmoniapy-1.2.0.dist-info/METADATA
harmoniapy-1.2.0.dist-info/WHEEL
harmoniapy-1.2.0.dist-info/entry_points.txt
harmoniapy-1.2.0.dist-info/top_level.txt
harmoniapy-1.2.0.dist-info/RECORD
