Metadata-Version: 2.2
Name: harmoniapy
Version: 1.2.0
Summary: Fast and accurate Python spell checker, a powerful alternative to pyspellchecker
Author-email: Dušan Jolović <jolovic@pm.me>
License: MIT License
Project-URL: Homepage, https://github.com/jolovicdev/harmonia
Keywords: spell,checker,spelling,correction,nlp
Classifier: Development Status :: 4 - Beta
Classifier: Intended Audience :: Developers
Classifier: License :: OSI Approved :: MIT License
Classifier: Programming Language :: Python :: 3.8
Classifier: Programming Language :: Python :: 3.9
Classifier: Programming Language :: Python :: 3.10
Classifier: Programming Language :: Python :: 3.11
Classifier: Topic :: Text Processing :: Linguistic
Classifier: Topic :: Text Processing :: Filters
Requires-Python: >=3.8
License-File: LICENSE
Requires-Dist: requests>=2.25.0
Requires-Dist: typing-extensions>=4.0.0
Requires-Dist: importlib-metadata>=1.0.0; python_version < "3.8"
